appmetrica_logs_api/__init__.py
appmetrica_logs_api/client.py
appmetrica_logs_api/constants.py
appmetrica_logs_api/exceptions.py
appmetrica_logs_api/schemas/clicks.py
appmetrica_logs_api/schemas/crashes.py
appmetrica_logs_api/schemas/deeplinks.py
appmetrica_logs_api/schemas/errors.py
appmetrica_logs_api/schemas/events.py
appmetrica_logs_api/schemas/installations.py
appmetrica_logs_api/schemas/postbacks.py
appmetrica_logs_api/schemas/profiles.py
appmetrica_logs_api/schemas/push_tokens.py
appmetrica_logs_api/schemas/revenue_events.py
appmetrica_logs_api/schemas/sessions_starts.py
appmetrica_logs_api-0.1.13.dist-info/METADATA
appmetrica_logs_api-0.1.13.dist-info/WHEEL
appmetrica_logs_api-0.1.13.dist-info/RECORD
